ezi/__init__.py
ezi/debit.py
ezi-1.0.0.dist-info/COPYING
ezi-1.0.0.dist-info/METADATA
ezi-1.0.0.dist-info/WHEEL
ezi-1.0.0.dist-info/top_level.txt
ezi-1.0.0.dist-info/RECORD
