Metadata-Version: 2.1
Name: ezi
Version: 1.0.0
Summary: Interface to the Ezidebit payment gateway for credit card and bank account payments.
Home-page: https://github.com/BenSturmfels/python-ezi
Author: Ben Sturmfels
Author-email: ben@sturm.com.au
License: UNKNOWN
Project-URL: Source, https://github.com/BenSturmfels/python-ezi
Project-URL: Bug Reports, https://github.com/BenSturmfels/python-ezi/issues
Platform: UNKNOWN
Classifier: Development Status :: 5 - Production/Stable
Classifier: Intended Audience :: Developers
Classifier: Topic :: Office/Business :: Financial
Classifier: License :: OSI Approved :: Apache Software License
Classifier: Programming Language :: Python :: 3
Requires-Python: >=3.6
Requires-Dist: suds-jurko (==0.6)
